[
    {
        "content": "<p>A dask notebook that was working last week is failing today with failed connection errors:<br>\nasyncio.exceptions.TimeoutError</p>\n<p>The error log files are here:<br>\n/glade/scratch/yeager/*.casper-pbs.ER</p>",
        "id": 44235,
        "sender_full_name": "Stephen Yeager",
        "timestamp": 1633365736
    },
    {
        "content": "<p>I think there is something up with the PBS scheduler on Casper this morning. I had similar issues yesterday; I submitted a help ticket with CISL, and I believe <span class=\"user-mention\" data-user-id=\"28\">@Kristen Krumhardt</span>  is planning on doing so as well.</p>",
        "id": 44237,
        "sender_full_name": "Max Grover",
        "timestamp": 1633365803
    },
    {
        "content": "<p>cc <span class=\"user-mention\" data-user-id=\"154\">@Jared Baker</span></p>",
        "id": 44238,
        "sender_full_name": "Matt Long",
        "timestamp": 1633365843
    },
    {
        "content": "<p>It seems that the <a href=\"https://www2.cisl.ucar.edu/user-support/cisl-resource-status\"><code>CISL Resource Status</code></a> page indicates that:</p>\n<div class=\"codehilite\"><pre><span></span><code>The Casper job scheduling system was not responding as of 11:11 10/04/2021.\nIf the problem persists, users will receive email updates through our Notifier service.\n</code></pre></div>",
        "id": 44247,
        "sender_full_name": "Max Grover",
        "timestamp": 1633367799
    }
]